travel_map/__init__.py
travel_map/core.py
travel_map/scripts/__init__.py
travel_map/scripts/commands.py
travel_map-2.0.1.dist-info/entry_points.txt
travel_map-2.0.1.dist-info/LICENSE
travel_map-2.0.1.dist-info/WHEEL
travel_map-2.0.1.dist-info/METADATA
travel_map-2.0.1.dist-info/RECORD
