Metadata-Version: 2.1
Name: travel-map
Version: 2.0.1
Summary: A tool to generate travel map.
Home-page: https://github.com/hktkzyx/travel-map
License: MulanPSL-2.0
Author: Brooks YUAN
Author-email: hktkzyx@yeah.net
Requires-Python: >=3.9,<4.0
Classifier: License :: OSI Approved
Classifier: License :: Other/Proprietary License
Classifier: Natural Language :: Chinese (Simplified)
Classifier: Natural Language :: English
Classifier: Programming Language :: Python :: 3
Classifier: Programming Language :: Python :: 3.10
Classifier: Programming Language :: Python :: 3.9
Provides-Extra: test
Requires-Dist: click (>=8.1.3,<9.0.0)
Requires-Dist: numpy (>=1.22.3,<2.0.0)
Requires-Dist: pandas (>=1.4.2,<2.0.0)
Requires-Dist: pyecharts (>=1.9.1,<2.0.0)
Requires-Dist: pytest (>=7.1.2,<8.0.0); extra == "test"
Requires-Dist: pytest-cov (>=3.0.0,<4.0.0); extra == "test"
Project-URL: Documentation, https://github.com/hktkzyx/travel-map
Project-URL: Repository, https://github.com/hktkzyx/travel-map
